prs_connector_core/__init__.py
prs_connector_core/config.py
prs_connector_core/connector.py
prs_connector_core/exceptions.py
prs_connector_core/times.py
prs_connector_core-0.8.0.dist-info/licenses/LICENSE
prs_connector_core-0.8.0.dist-info/METADATA
prs_connector_core-0.8.0.dist-info/WHEEL
prs_connector_core-0.8.0.dist-info/top_level.txt
prs_connector_core-0.8.0.dist-info/RECORD
