Metadata-Version: 2.4
Name: prs_connector_core
Version: 0.8.0
Summary: Базовый модуль для коннекторов платформы Пересвет
Author-email: ООО МПК <info@mp-co.ru>
License: Apache-2.0
Project-URL: Homepage, https://github.com/mp-co-ru/prs-connector-core
Project-URL: Repository, https://github.com/mp-co-ru/prs-connector-core
Project-URL: Documentation, https://mp-co-ru.github.io/prs-connector-core/
Classifier: Programming Language :: Python :: 3
Classifier: License :: OSI Approved :: Apache Software License
Classifier: Operating System :: OS Independent
Requires-Python: >=3.12
License-File: LICENSE
Requires-Dist: aiomqtt==2.3.2
Requires-Dist: jsonata-python==0.5.3
Requires-Dist: colorlog==6.9.0
Requires-Dist: python-json-logger==3.3.0
Requires-Dist: pydantic==2.11.3
Requires-Dist: pydantic_core==2.33.1
Requires-Dist: aiofiles==24.1.0
Requires-Dist: ciso8601==2.3.2
Requires-Dist: python-dateutil==2.9.0.post0
Dynamic: license-file
